Metadata-Version: 2.4
Name: common_stats_nawawan
Version: 0.0.1
Summary: A simple library for basic statistical calculations
Author: Paras Arora
Author-email: parasarora@email.com
License: MIT
Requires-Python: >=3.7
License-File: LICENSE
Requires-Dist: pytest
Dynamic: author
Dynamic: author-email
Dynamic: description
Dynamic: description-content-type
Dynamic: license
Dynamic: license-file
Dynamic: requires-dist
Dynamic: requires-python
Dynamic: summary
